splashgen/__init__.py
splashgen/cli.py
splashgen/integrations.py
splashgen/assets/SplashGen.png
splashgen/assets/logo-default.png
splashgen/components/CTAButton.py
splashgen/components/SplashSite.py
splashgen/components/__init__.py
splashgen/components/form.py
splashgen/templates/form.html.jinja
splashgen/templates/github_log_template.html.jinja
splashgen/templates/input.html.jinja
splashgen/templates/mailchimp_signup.html.jinja
splashgen/templates/splash_site.html.jinja
splashgen-0.0.29.dist-info/LICENSE
splashgen-0.0.29.dist-info/METADATA
splashgen-0.0.29.dist-info/WHEEL
splashgen-0.0.29.dist-info/entry_points.txt
splashgen-0.0.29.dist-info/top_level.txt
splashgen-0.0.29.dist-info/RECORD
