Metadata-Version: 2.1
Name: splashgen
Version: 0.0.29
Summary: Create a splash page in less than 20 lines of python
Home-page: https://github.com/true3dco/splashgen
Author: True3D
Author-email: founders@true3d.live
License: MIT
Platform: UNKNOWN
Classifier: License :: OSI Approved :: MIT License
Classifier: Programming Language :: Python :: 3
Classifier: Programming Language :: Python :: 3.7
Requires-Dist: Jinja2
Requires-Dist: query-string
Requires-Dist: urlexpander
Requires-Dist: pillow
Requires-Dist: python-slugify
Requires-Dist: urlextract
Requires-Dist: py3-validate-email
